ddopai/RL_approximators.py
ddopai/__init__.py
ddopai/_modidx.py
ddopai/approximators.py
ddopai/loss_functions.py
ddopai/utils.py
ddopai/agents/__init__.py
ddopai/agents/base.py
ddopai/agents/basic.py
ddopai/agents/class_names.py
ddopai/agents/ml_utils.py
ddopai/agents/obsprocessors.py
ddopai/agents/newsvendor/__init__.py
ddopai/agents/newsvendor/erm.py
ddopai/agents/newsvendor/saa.py
ddopai/agents/rl/__init__.py
ddopai/agents/rl/mushroom_rl.py
ddopai/agents/rl/ppo.py
ddopai/agents/rl/sac.py
ddopai/agents/rl/td3.py
ddopai/dataloaders/__init__.py
ddopai/dataloaders/base.py
ddopai/dataloaders/distribution.py
ddopai/dataloaders/tabular.py
ddopai/datasets/__init__.py
ddopai/datasets/bakery.py
ddopai/datasets/default_datasets.py
ddopai/datasets/kaggle_m5.py
ddopai/datasets/utils.py
ddopai/envs/__init__.py
ddopai/envs/actionprocessors.py
ddopai/envs/base.py
ddopai/envs/inventory/__init__.py
ddopai/envs/inventory/base.py
ddopai/envs/inventory/inventory_utils.py
ddopai/envs/inventory/multi_period.py
ddopai/envs/inventory/single_period.py
ddopai/experiments/__init__.py
ddopai/experiments/experiment_functions.py
ddopai/experiments/meta_experiment_functions.py
ddopai/experiments/tracking.py
ddopai/torch_utils/__init__.py
ddopai/torch_utils/loss_functions.py
ddopai-0.0.8.dist-info/LICENSE
ddopai-0.0.8.dist-info/METADATA
ddopai-0.0.8.dist-info/WHEEL
ddopai-0.0.8.dist-info/entry_points.txt
ddopai-0.0.8.dist-info/top_level.txt
ddopai-0.0.8.dist-info/RECORD
