Metadata-Version: 2.1
Name: ddopai
Version: 0.0.8
Summary: A completely new version of ddop. New name to be specificed.
Home-page: https://github.com/opimwue/ddopai
Author: kaiguender
Author-email: kai.guender@yahoo.de
License: Apache Software License 2.0
Keywords: nbdev jupyter notebook python
Classifier: Development Status :: 4 - Beta
Classifier: Intended Audience :: Developers
Classifier: Natural Language :: English
Classifier: Programming Language :: Python :: 3.7
Classifier: Programming Language :: Python :: 3.8
Classifier: Programming Language :: Python :: 3.9
Classifier: Programming Language :: Python :: 3.10
Classifier: License :: OSI Approved :: Apache Software License
Requires-Python: >=3.7
License-File: LICENSE
Requires-Dist: fastcore
Requires-Dist: pandas
Requires-Dist: numpy
Requires-Dist: gymnasium ==0.28.1
Requires-Dist: scikit-learn ==1.5.1
Requires-Dist: requests
Requires-Dist: tqdm
Requires-Dist: mushroom-rl ==1.10.1
Requires-Dist: torchinfo
Requires-Dist: xgboost
Requires-Dist: wandb
Provides-Extra: dev
